{
  "tags": {
    "allowUnknownTags": true
  },
  "source": {
    "include": [
      "./node_modules/jsdoc/",
      "./templates/default/publish.js"
    ]
  },
  "plugins": [
  ],
  "opts": {
    "encoding": "utf8",
    "template": "./templates/default/",
    "destination": "./templates/default/generated-files/",
    "recurse": true,
    "verbose": true
  },
  "markdown": {
    "parser": "gfm",
    "hardwrap": true
  },
  "templates": {
    "cleverLinks": false,
    "monospaceLinks": false,
    "default": {
      "outputSourceFiles": true,
      "includeDate": false
    }
  },
  "powerMode": {
    "displayStaticMembers": false,
    "sort": true
  }
}
